entity_type_local/__init__.py
entity_type_local/entity_enum.py
entity_type_local/entity_type.py
entity_type_local/entity_types_local.py
entity_type_local-0.0.35.dist-info/METADATA
entity_type_local-0.0.35.dist-info/WHEEL
entity_type_local-0.0.35.dist-info/top_level.txt
entity_type_local-0.0.35.dist-info/RECORD
