Metadata-Version: 2.4
Name: entity-type-local
Version: 0.0.35
Summary: PyPI Package for Circles smart link Python
Home-page: https://github.com/circles-zone/entity-type-local-python-package
Author: Circles
Author-email: info@circlez.ai
Classifier: Programming Language :: Python :: 3
Classifier: Operating System :: OS Independent
Requires-Dist: logger-local>=0.0.76
Requires-Dist: database-mysql-local>=0.1.49
Dynamic: author
Dynamic: author-email
Dynamic: classifier
Dynamic: description
Dynamic: description-content-type
Dynamic: home-page
Dynamic: requires-dist
Dynamic: summary
